color/__init__.py
color/color.py
color/func/__init__.py
color/func/color_cmd.py
color/func/color_sh.py
color_print-0.1.0.dist-info/DESCRIPTION.rst
color_print-0.1.0.dist-info/METADATA
color_print-0.1.0.dist-info/RECORD
color_print-0.1.0.dist-info/WHEEL
color_print-0.1.0.dist-info/metadata.json
color_print-0.1.0.dist-info/top_level.txt
