Metadata-Version: 2.0
Name: color-print
Version: 0.1.0
Summary: A color print wrapper
Home-page: https://github.com/minghu6/color_print
Author: minghu6
Author-email: a19678zy@163.com
License: BSD License
Platform: UNKNOWN
Classifier: Development Status :: 5 - Production/Stable
Classifier: Intended Audience :: Developers
Classifier: License :: OSI Approved :: BSD License
Classifier: Operating System :: OS Independent
Classifier: Programming Language :: Python :: 2
Classifier: Programming Language :: Python :: 3
Classifier: Programming Language :: Python :: Implementation :: CPython
Classifier: Programming Language :: Python :: Implementation :: PyPy
